berhoel/imdb_extract/__init__.py
"berhoel/imdb_extract/__init__.py,cover"
berhoel/imdb_extract/py.typed
berhoel/imdb_extract/tests/.ruff.toml
berhoel/imdb_extract/tests/.ruff_cache/.gitignore
berhoel/imdb_extract/tests/.ruff_cache/0.8.6/2499576934390540913
berhoel/imdb_extract/tests/.ruff_cache/0.8.6/6993800263675516320
berhoel/imdb_extract/tests/.ruff_cache/0.9.1/642873418702342189
berhoel/imdb_extract/tests/.ruff_cache/0.9.1/7295270032313094238
berhoel/imdb_extract/tests/.ruff_cache/0.9.10/15377748408558297699
berhoel/imdb_extract/tests/.ruff_cache/0.9.4/11717588728107801726
berhoel/imdb_extract/tests/.ruff_cache/0.9.4/852336372840570480
berhoel/imdb_extract/tests/.ruff_cache/0.9.6/16964653079165956334
berhoel/imdb_extract/tests/.ruff_cache/0.9.6/2306892311862321490
berhoel/imdb_extract/tests/.ruff_cache/CACHEDIR.TAG
berhoel/imdb_extract/tests/__init__.py
berhoel/imdb_extract/tests/conftest.py
berhoel/imdb_extract/tests/test_base.py
berhoel/imdb_extract/tests/test_unicodewriter.py
berhoel/imdb_extract/unicodewriter.py
"berhoel/imdb_extract/unicodewriter.py,cover"
imdb_extract-2.5.3.dist-info/WHEEL
imdb_extract-2.5.3.dist-info/entry_points.txt
imdb_extract-2.5.3.dist-info/METADATA
imdb_extract-2.5.3.dist-info/RECORD
