Metadata-Version: 2.3
Name: imdb-extract
Version: 2.5.3
Summary: Download IMDB series information.
Author: Berthold Höllmann
Author-email: Berthold Höllmann <berthold-gitlab@xn--hllmanns-n4a.de>
License: BSD
Classifier: Development Status :: 4 - Beta
Classifier: License :: OSI Approved :: BSD License
Classifier: Programming Language :: Python
Classifier: Programming Language :: Python :: Implementation :: CPython
Classifier: Operating System :: OS Independent
Requires-Dist: click
Requires-Dist: lxml
Requires-Dist: requests
Requires-Dist: rich
Requires-Dist: playwright
Maintainer: Berthold Höllmann
Maintainer-email: Berthold Höllmann <berthold-gitlab@xn--hllmanns-n4a.de>
Requires-Python: >=3.13, <4.0
Project-URL: Documentation, https://python.xn--hllmanns-n4a.de/IMDBExtract/
Project-URL: Homepage, https://python.xn--hllmanns-n4a.de/IMDBExtract/
Project-URL: Repository, https://gitlab.com/berhoel/python/IMDBExtract
